htmlLibrarian/__init__.py
htmlLibrarian/librarian.py
htmlLibrarian/librarianUtil.py
htmlLibrarian/linkData.py
htmlLibrarian/tests/__init__.py
htmlLibrarian/tests/clean_test.py
htmlLibrarian/tests/context.py
htmlLibrarian/tests/debug_mode_print_test.py
htmlLibrarian/tests/example_test.py
htmlLibrarian/tests/get_fetch_flow_test.py
htmlLibrarian/tests/make_csv_test.py
htmlLibrarian-0.0.14.dist-info/METADATA
htmlLibrarian-0.0.14.dist-info/RECORD
htmlLibrarian-0.0.14.dist-info/WHEEL
htmlLibrarian-0.0.14.dist-info/top_level.txt
