Metadata-Version: 1.0
Name: htmlLibrarian
Version: 0.0.14
Summary: Never ever scrape the html off of a site multiple times ever again.
Home-page: https://github.com/alexsieusahai/htmlLibrarian
Author: Alex Sieusahai
Author-email: alexsieu14@gmail.com
License: MIT License
Platform: UNKNOWN
